Metadata-Version: 2.1
Name: yolo34py-gpu
Version: 0.2rc5
Summary: Python wrapper on YOLO 3.0 implementation by 'pjreddie': (https://pjreddie.com/yolo)
Home-page: https://github.com/madhawav/YOLO3-4-Py
Author: Madhawa Vidanapathirana
Author-email: madhawavidanapathirana@gmail.com
License: YOLO34Py wrapper is under Apache 2.0. Darknet is Public Domain.
Keywords: yolo darknet object detection vision
Platform: linux-x86_64
Classifier: Development Status :: 4 - Beta
Classifier: License :: OSI Approved :: Apache Software License
Classifier: Programming Language :: Python :: 3.5
Classifier: Programming Language :: Python :: 3.6
Classifier: Programming Language :: Python :: 3.7
Classifier: Topic :: Text Processing :: Linguistic
Classifier: Operating System :: POSIX :: Linux
Classifier: Intended Audience :: Science/Research
Classifier: Topic :: Scientific/Engineering :: Artificial Intelligence
Requires-Python: >=3.5
